scStateDynamics/__init__.py
scStateDynamics/scStateDynamics.py
scStateDynamics-0.0.20.dist-info/LICENSE
scStateDynamics-0.0.20.dist-info/METADATA
scStateDynamics-0.0.20.dist-info/WHEEL
scStateDynamics-0.0.20.dist-info/top_level.txt
scStateDynamics-0.0.20.dist-info/RECORD
