Metadata-Version: 2.1
Name: scStateDynamics
Version: 0.0.20
Summary: A package to decipher the drug-responsive tumor cell state dynamics by modeling single-cell level expression changes
Home-page: https://github.com/wguo-research/scStateDynamics
Author: Wenbo Guo
Author-email: gwb17@tsinghua.org.cn
License: MIT
Platform: UNKNOWN
Requires-Python: >=3.7
License-File: LICENSE
Requires-Dist: numpy
Requires-Dist: pandas
Requires-Dist: scipy
Requires-Dist: scikit-learn
Requires-Dist: torch
Requires-Dist: seaborn
Requires-Dist: matplotlib
Requires-Dist: scanpy
Requires-Dist: leidenalg
Requires-Dist: pyro-ppl
Requires-Dist: POT
